AUTHORS.rst
CONTRIBUTING.rst
HISTORY.rst
LICENSE
MANIFEST.in
README.rst
setup.py
sc2castsclient/__init__.py
sc2castsclient/client.py
sc2castsclient/model.py
sc2castsclient/parser.py
sc2castsclient.egg-info/PKG-INFO
sc2castsclient.egg-info/SOURCES.txt
sc2castsclient.egg-info/dependency_links.txt
sc2castsclient.egg-info/not-zip-safe
sc2castsclient.egg-info/top_level.txt