Metadata-Version: 1.1
Name: sc2castsclient
Version: 0.1.0
Summary: Client for crawling sc2casts.com, in python
Home-page: https://github.com/thmttch/sc2castsclient
Author: Matt Chu
Author-email: matt.chu@gmail.com
License: BSD
Keywords: sc2castsclient
Platform: UNKNOWN
Classifier: Development Status :: 2 - Pre-Alpha
Classifier: Intended Audience :: Developers
Classifier: License :: OSI Approved :: BSD License
Classifier: Natural Language :: English
Classifier: Programming Language :: Python :: 2
Classifier: Programming Language :: Python :: 2.6
Classifier: Programming Language :: Python :: 2.7
Classifier: Programming Language :: Python :: 3
Classifier: Programming Language :: Python :: 3.3
